matchbox/__init__.py
matchbox/box.py
matchbox/index.py
matchbox-1.3.0.dist-info/licenses/AUTHORS.rst
matchbox-1.3.0.dist-info/licenses/LICENSE
matchbox-1.3.0.dist-info/METADATA
matchbox-1.3.0.dist-info/WHEEL
matchbox-1.3.0.dist-info/top_level.txt
matchbox-1.3.0.dist-info/zip-safe
matchbox-1.3.0.dist-info/RECORD
