Metadata-Version: 2.4
Name: matchbox
Version: 1.3.0
Summary: Abstraction layer for creating hash maps to speed up extracting subsets out of objects in collection
Author-email: Grzegorz Śliwiński <fizyk+pypi@fizyk.dev>
License:                    GNU LESSER GENERAL PUBLIC LICENSE
Project-URL: Source, https://github.com/fizyk/matchbox
Project-URL: Bug Tracker, https://github.com/fizyk/matchbox/issues
Project-URL: Changelog, https://github.com/fizyk/matchbox/blob/v1.3.0/CHANGES.rst
Project-URL: Documentation, http://fizyk.github.io/matchbox/
Keywords: index,match,set,hashmap
Classifier: Development Status :: 5 - Production/Stable
Classifier: Intended Audience :: Developers
Classifier: License :: OSI Approved :: GNU Lesser General Public License v3 or later (LGPLv3+)
Classifier: Natural Language :: English
Classifier: Operating System :: OS Independent
Classifier: Programming Language :: Python
Classifier: Programming Language :: Python :: 3
Classifier: Programming Language :: Python :: 3.10
Classifier: Programming Language :: Python :: 3.11
Classifier: Programming Language :: Python :: 3.12
Classifier: Programming Language :: Python :: 3.13
Classifier: Programming Language :: Python :: 3.14
Classifier: Programming Language :: Python :: 3 :: Only
Classifier: Topic :: Software Development :: Libraries :: Python Modules
Requires-Python: >=3.10
License-File: LICENSE
License-File: AUTHORS.rst
Provides-Extra: docs
Requires-Dist: sphinx; extra == "docs"
Dynamic: license-file
